{"is_source_file": false, "format": "", "description": "", "external_files": [], "external_methods": [], "published": [], "classes": [], "methods": [], "calls": [], "search-terms": ["React template", "tic-tac-toe", "AI opponent", "chat panel", "responsive layout", "environment variables", "npm scripts", "React documentation", "frontend", "README.md"], "state": 2, "file_id": 2, "knowledge_revision": 30, "git_revision": "e711437e628d786becf6bcbfdd75ae7bd6e52dfb", "hash": "d677bcc83475b019ff1e6de839cd8776", "format-version": 4, "code-base-name": "tic_tac_toe_frontend", "filename": "tic_tac_toe_frontend/README.md", "revision_history": [{"30": "e711437e628d786becf6bcbfdd75ae7bd6e52dfb"}]}